main.py
DunkinDonut-1.0.0.dist-info/METADATA
DunkinDonut-1.0.0.dist-info/WHEEL
DunkinDonut-1.0.0.dist-info/entry_points.txt
DunkinDonut-1.0.0.dist-info/top_level.txt
DunkinDonut-1.0.0.dist-info/RECORD
